jhbox/__init__.py
jhbox/box.py
jhbox-0.0.3.dist-info/LICENSE
jhbox-0.0.3.dist-info/METADATA
jhbox-0.0.3.dist-info/WHEEL
jhbox-0.0.3.dist-info/top_level.txt
jhbox-0.0.3.dist-info/RECORD
