Metadata-Version: 2.1
Name: jhbox
Version: 0.0.3
Summary: A Python Tool Box
Home-page: https://github.com/jin-hao-chen/jhbox
Author: Chen Jinhao
Author-email: jin_hao_chen@163.com
License: UNKNOWN
Platform: UNKNOWN
Classifier: Programming Language :: Python :: 3
Classifier: License :: OSI Approved :: MIT License
Classifier: Operating System :: OS Independent
